{
  "products": [
    {
      "name": "Audi 250",
      "price": "500000",
      "owner": "admiralty20",
      "last_bidder": "samson35"
    },
    {
      "name": "Lamborghini S50",
      "price": "2000005",
      "owner": "susaske40",
      "last_bidder": "dviartseika"
    },
    {
      "name": "Ferrari F560",
      "price": "100000",
      "owner": "samson35",
      "last_bidder": "admiralty20"
    },
    {
      "name": "5",
      "price": "055",
      "owner": "wertey"
    },
    {
      "name": "ч",
      "price": "34343",
      "owner": "dviartseika",
      "last_bidder": "dviartseika"
    },
    {
      "name": "test",
      "price": "545",
      "owner": "dviartseika"
    }
  ]
}